testtools1
tools
