Metadata-Version: 2.1
Name: testtools1
Version: 1.0.4
Summary: EthTools framework
Home-page: https://github.com/Kefirock/testtools1
Author: TakeWing
Author-email: n.ostroukhov@takewing.ru
License: UNKNOWN
Platform: UNKNOWN
Classifier: Programming Language :: Python :: 3
Classifier: License :: OSI Approved :: MIT License
Classifier: Operating System :: OS Independent
